blitzortung/__init__.py
blitzortung/base.py
blitzortung/builder/__init__.py
blitzortung/builder/base.py
blitzortung/builder/strike.py
blitzortung/cache.py
blitzortung/cli/__init__.py
blitzortung/cli/db.py
blitzortung/cli/imprt.py
blitzortung/cli/imprt_websocket.py
blitzortung/cli/start_webservice.py
blitzortung/cli/update.py
blitzortung/cli/webservice.py
blitzortung/cli/webservice_insertlog.py
blitzortung/config.py
blitzortung/convert.py
blitzortung/data.py
blitzortung/dataimport/__init__.py
blitzortung/dataimport/base.py
blitzortung/dataimport/strike.py
blitzortung/db/__init__.py
blitzortung/db/compat.py
blitzortung/db/grid_result.py
blitzortung/db/mapper.py
blitzortung/db/query.py
blitzortung/db/query_builder.py
blitzortung/db/table.py
blitzortung/geom.py
blitzortung/gis/__init__.py
blitzortung/gis/constants.py
blitzortung/gis/local_grid.py
blitzortung/lock.py
blitzortung/logger.py
blitzortung/service/__init__.py
blitzortung/service/cache.py
blitzortung/service/db.py
blitzortung/service/general.py
blitzortung/service/histogram.py
blitzortung/service/metrics.py
blitzortung/service/strike.py
blitzortung/service/strike_grid.py
blitzortung/util.py
blitzortung/websocket.py
blitzortung-1.11.34.dist-info/METADATA
blitzortung-1.11.34.dist-info/WHEEL
blitzortung-1.11.34.dist-info/entry_points.txt
blitzortung-1.11.34.dist-info/licenses/LICENSE
blitzortung-1.11.34.dist-info/RECORD
