Metadata-Version: 2.4
Name: blitzortung
Version: 1.11.34
Summary: blitzortung.org python modules
License-Expression: Apache-2.0
License-File: LICENSE
Author: Andreas Würl
Author-email: andi@tryb.de
Requires-Python: >=3.11,<4.0
Classifier: Programming Language :: Python :: 3
Classifier: Programming Language :: Python :: 3.11
Classifier: Programming Language :: Python :: 3.12
Classifier: Programming Language :: Python :: 3.13
Classifier: Programming Language :: Python :: 3.14
Requires-Dist: fasteners (>=0.19)
Requires-Dist: geoip2 (>=5.1)
Requires-Dist: incremental (>=22.10)
Requires-Dist: injector (>=0.22)
Requires-Dist: psycopg2 (>=2.9)
Requires-Dist: psycopg2cffi (>=2.9)
Requires-Dist: pyproj (>=3.7)
Requires-Dist: requests (>=2.32)
Requires-Dist: shapely (>=2.0)
Requires-Dist: statsd (>=4.0)
Requires-Dist: stopit (>=1.1)
Requires-Dist: twisted (>=25.5)
Requires-Dist: txjsonrpc-ng (>=0.8)
Requires-Dist: txpostgres (>=1.7)
Requires-Dist: websocket-client (>=1.9)
